xlsx_split.py
xlsx_split-0.1.1.dist-info/LICENSE
xlsx_split-0.1.1.dist-info/METADATA
xlsx_split-0.1.1.dist-info/WHEEL
xlsx_split-0.1.1.dist-info/entry_points.txt
xlsx_split-0.1.1.dist-info/top_level.txt
xlsx_split-0.1.1.dist-info/RECORD
