Metadata-Version: 2.1
Name: xlsx-split
Version: 0.1.1
Summary: Excel表格分割工具。
Home-page: https://github.com/appstore-zencore/xlsx-split
Author: zencore
Author-email: dobetter@zencore.cn
License: MIT
Keywords: openpyxl,xlsx split,excel split
Platform: UNKNOWN
Classifier: Development Status :: 5 - Production/Stable
Classifier: Intended Audience :: Developers
Classifier: Topic :: Software Development :: Libraries :: Python Modules
Classifier: License :: OSI Approved :: MIT License
Classifier: Programming Language :: Python :: 3
Classifier: Programming Language :: Python :: 3 :: Only
Requires: click
Requires: openpyxl
Requires: xlsxhelper
Requires-Dist: click
Requires-Dist: openpyxl
Requires-Dist: xlsxhelper
